autofast/__init__.py
autofast/config/__init__.py
autofast/config/deserialization.py
autofast/config/deserialize_aux.py
autofast/config/enum.py
autofast/config/serialization.py
autofast/config/data/__init__.py
autofast/config/data/configuration_options.py
autofast/config/data/field_meta_data.py
autofast/config/error/__init__.py
autofast/config/error/config_parse_error.py
autofast/config/error/field_parse_error.py
autofast/config/parse_graph/__init__.py
autofast/config/parse_graph/node.py
autofast/injection/__init__.py
autofast/injection/container.py
autofast/injection/validation/__init__.py
autofast/injection/validation/constructor.py
autofast/injection/validation/function.py
autofast/injection/validation/graph.py
autofast/injection/validation/inheritance.py
autofast/injection/validation/transitive.py
autofast/reflection/__init__.py
autofast/reflection/class_reflect.py
autofast/reflection/function.py
autofast/reflection/generic.py
autofast/reflection/meta.py
autofast/reflection/data/__init__.py
autofast/reflection/data/argument_meta_info.py
autofast/reflection/data/class_meta_info.py
autofast/reflection/data/function_meta_info.py
autofast/verify/__init__.py
autofast/verify/object_verify.py
autofast-0.3.0.dist-info/LICENSE
autofast-0.3.0.dist-info/METADATA
autofast-0.3.0.dist-info/WHEEL
autofast-0.3.0.dist-info/top_level.txt
autofast-0.3.0.dist-info/RECORD
